cli_tool.py
thanker/__init__.py
thanker/_group_by.py
thanker/_scanner.py
thanker/_thanker.py
thanker/test_thanker.py
thanker/web/__init__.py
thanker/web/assets/css/styles.css
thanker/web/template/index.html
thanker-0.0.6.dist-info/LICENSE
thanker-0.0.6.dist-info/METADATA
thanker-0.0.6.dist-info/WHEEL
thanker-0.0.6.dist-info/entry_points.txt
thanker-0.0.6.dist-info/top_level.txt
thanker-0.0.6.dist-info/RECORD
