Metadata-Version: 2.1
Name: thanker
Version: 0.0.6
Summary: Don
Home-page: https://github.com/WardPearce/thanker
Author: WardPearce
Author-email: wardpearce@protonmail.com
License: Apache-2.0
Platform: UNKNOWN
Requires-Python: >=3.6
License-File: LICENSE
Requires-Dist: aiohttp
Requires-Dist: click
Requires-Dist: asynctest
Requires-Dist: aiofiles
Requires-Dist: starlette
Requires-Dist: uvicorn
Requires-Dist: python-multipart
Requires-Dist: jinja2
